magnetometer/__init__.py
magnetometer/__main__.py
magnetometer/asciichartpy.py
magnetometer/dependencies/main/adafruit_bus_device/__init__.py
magnetometer/dependencies/main/adafruit_bus_device/i2c_device.py
magnetometer/dependencies/main/adafruit_bus_device/spi_device.py
magnetometer/dependencies/main/adafruit_lis2mdl/__init__.py
magnetometer/dependencies/main/adafruit_lis3mdl/__init__.py
magnetometer/dependencies/main/adafruit_mmc56x3/__init__.py
magnetometer/dependencies/main/adafruit_register/__init__.py
magnetometer/dependencies/main/adafruit_register/i2c_bcd_alarm.py
magnetometer/dependencies/main/adafruit_register/i2c_bcd_datetime.py
magnetometer/dependencies/main/adafruit_register/i2c_bit.py
magnetometer/dependencies/main/adafruit_register/i2c_bits.py
magnetometer/dependencies/main/adafruit_register/i2c_struct.py
magnetometer/dependencies/main/adafruit_register/i2c_struct_array.py
magnetometer/dependencies/main/adafruit_tlv493d/__init__.py
magnetometer/main.py
magnetometer/sensors/__init__.py
magnetometer/sensors/base.py
magnetometer/sensors/lis2mdl.py
magnetometer/sensors/lis3mdl.py
magnetometer/sensors/mmc56x3.py
magnetometer/sensors/sin.py
magnetometer/sensors/tlv493d.py
magnetometer-0.2.1.dist-info/METADATA
magnetometer-0.2.1.dist-info/entry_points.txt
magnetometer-0.2.1.dist-info/WHEEL
magnetometer-0.2.1.dist-info/LICENSE
magnetometer-0.2.1.dist-info/RECORD
