Metadata-Version: 2.1
Name: magnetometer
Version: 0.2.1
Summary: 
Home-page: https://github.com/BrianPugh/magnetometer
License: Apache-2.0
Author: Brian Pugh
Requires-Python: >=3.8,<4.0
Classifier: License :: OSI Approved :: Apache Software License
Classifier: Programming Language :: Python :: 3
Classifier: Programming Language :: Python :: 3.8
Classifier: Programming Language :: Python :: 3.9
Classifier: Programming Language :: Python :: 3.10
Classifier: Programming Language :: Python :: 3.11
Requires-Dist: autoregistry (>=0.8,<0.9)
Requires-Dist: belay (>=0.17.0,<0.18.0)
Requires-Dist: textual (>=0.1.18,<0.2.0)
Requires-Dist: typer[all] (>=0.6,<0.7)
Project-URL: Repository, https://github.com/BrianPugh/magnetometer
